dagfactory/__init__.py
dagfactory/__main__.py
dagfactory/_yaml.py
dagfactory/constants.py
dagfactory/dagbuilder.py
dagfactory/dagfactory.py
dagfactory/exceptions.py
dagfactory/parsers.py
dagfactory/settings.py
dagfactory/telemetry.py
dagfactory/utils.py
dagfactory/listeners/__init__.py
dagfactory/listeners/runtime_event.py
dagfactory/plugin/__init__.py
dag_factory-1.0.1.dist-info/METADATA
dag_factory-1.0.1.dist-info/WHEEL
dag_factory-1.0.1.dist-info/entry_points.txt
dag_factory-1.0.1.dist-info/licenses/LICENSE
dag_factory-1.0.1.dist-info/RECORD
