Metadata-Version: 2.4
Name: dag-factory
Version: 1.0.1
Summary: Dynamically build Apache Airflow DAGs from YAML files
Project-URL: Source, https://github.com/astronomer/dag-factory
Author-email: Astronomer <humans@astronomer.io>
License-Expression: Apache-2.0
License-File: LICENSE
Keywords: airflow,apache-airflow,astronomer,dag,provider
Classifier: Development Status :: 5 - Production/Stable
Classifier: Framework :: Apache Airflow
Classifier: Intended Audience :: Developers
Classifier: License :: OSI Approved :: Apache Software License
Classifier: Programming Language :: Python :: 3
Classifier: Programming Language :: Python :: 3 :: Only
Classifier: Programming Language :: Python :: 3.9
Classifier: Programming Language :: Python :: 3.10
Classifier: Programming Language :: Python :: 3.11
Classifier: Programming Language :: Python :: 3.12
Classifier: Programming Language :: Python :: Implementation :: CPython
Classifier: Programming Language :: Python :: Implementation :: PyPy
Classifier: Topic :: Database
Requires-Python: >=3.9
Requires-Dist: apache-airflow>=2.4
Requires-Dist: packaging
Requires-Dist: pyyaml
Requires-Dist: typer
Provides-Extra: all
Requires-Dist: apache-airflow-providers-cncf-kubernetes>=4.4.0; extra == 'all'
Requires-Dist: apache-airflow-providers-common-sql>=1.2.0; extra == 'all'
Requires-Dist: apache-airflow-providers-http>=4.0.0; extra == 'all'
Requires-Dist: apache-airflow>=2.4; extra == 'all'
Requires-Dist: packaging; extra == 'all'
Requires-Dist: pyyaml; extra == 'all'
Provides-Extra: common-sql
Requires-Dist: apache-airflow-providers-common-sql>=1.2.0; extra == 'common-sql'
Provides-Extra: http
Requires-Dist: apache-airflow-providers-http>=4.0.0; extra == 'http'
Provides-Extra: kubernetes
Requires-Dist: apache-airflow-providers-cncf-kubernetes>=4.4.0; extra == 'kubernetes'
Provides-Extra: tests
Requires-Dist: apache-airflow-providers-cncf-kubernetes>=4.4.0; extra == 'tests'
Requires-Dist: apache-airflow-providers-common-sql>=1.2.0; extra == 'tests'
Requires-Dist: apache-airflow-providers-http>=4.0.0; extra == 'tests'
Requires-Dist: apache-airflow-providers-slack; extra == 'tests'
Requires-Dist: pre-commit; extra == 'tests'
Requires-Dist: pytest-cov; extra == 'tests'
Requires-Dist: pytest>=6.0; extra == 'tests'
